CrawlSpider/__init__.py
CrawlSpider/ETL/BaseETL.py
CrawlSpider/ETL/__init__.py
CrawlSpider/Utils/AliSDK.py
CrawlSpider/Utils/AwsSDK.py
CrawlSpider/Utils/BodyParser.py
CrawlSpider/Utils/DateUtils.py
CrawlSpider/Utils/FileUpload.py
CrawlSpider/Utils/FileUtils.py
CrawlSpider/Utils/FindGrep.py
CrawlSpider/Utils/Helper.py
CrawlSpider/Utils/MySQLDb.py
CrawlSpider/Utils/MySQLDbSync.py
CrawlSpider/Utils/OfficeUtils.py
CrawlSpider/Utils/PgDb.py
CrawlSpider/Utils/PgDbAsync.py
CrawlSpider/Utils/RedisDB.py
CrawlSpider/Utils/ResHandler.py
CrawlSpider/Utils/RetrieveProxy.py
CrawlSpider/Utils/RetrieveUA.py
CrawlSpider/Utils/SQLib.py
CrawlSpider/Utils/SQLibs.py
CrawlSpider/Utils/Settings.py
CrawlSpider/Utils/SpiderRequest.py
CrawlSpider/Utils/SpiderRequestSync.py
CrawlSpider/Utils/SplashHandler.py
CrawlSpider/Utils/ThreadClosable.py
CrawlSpider/Utils/__init__.py
CrawlSpider/Utils/__main__.py
CrawlSpider/Utils/monitor.py
CrawlSpider/Utils/taskUtils.py
CrawlSpider/Utils/twineUtils.py
CrawlSpider/conf/__init__.py
CrawlSpider/conf/settings.py
CrawlSpider/cos_sdk/__init__.py
CrawlSpider/cos_sdk/TencentCloud/CosOp.py
CrawlSpider/cos_sdk/TencentCloud/MyCosS3Client.py
CrawlSpider/cos_sdk/TencentCloud/MyFileStream.py
CrawlSpider/cos_sdk/TencentCloud/__init__.py
CrawlSpider/date_infer/__init__.py
CrawlSpider/date_infer/date_elements.py
CrawlSpider/date_infer/infer.py
CrawlSpider/date_infer/ruleproc.py
CrawlSpider/dun_sdk/TextBatchCheck.py
CrawlSpider/dun_sdk/__init__.py
CrawlSpider/spiders/BaseNewsSpider.py
CrawlSpider/spiders/NewsSpider.py
CrawlSpider/spiders/__init__.py
test/__init__.py
test/config.py
test/dateInfer.py
test/splash.py
CrawlSpider-2.0.8.dist-info/METADATA
CrawlSpider-2.0.8.dist-info/WHEEL
CrawlSpider-2.0.8.dist-info/entry_points.txt
CrawlSpider-2.0.8.dist-info/top_level.txt
CrawlSpider-2.0.8.dist-info/RECORD
